fp3/__init__.py
fp3-0.0.1.dist-info/LICENSE
fp3-0.0.1.dist-info/METADATA
fp3-0.0.1.dist-info/WHEEL
fp3-0.0.1.dist-info/entry_points.txt
fp3-0.0.1.dist-info/top_level.txt
fp3-0.0.1.dist-info/RECORD
