Metadata-Version: 2.1
Name: fp3
Version: 0.0.1
Summary: Faster Parallel Processing Pipeline
Home-page: UNKNOWN
Author: Diamond Light Source - Scientific Software
Author-email: scientificsoftware@diamond.ac.uk
License: BSD 3-Clause License
Project-URL: GitHub, https://github.com/xia2/fp3
Project-URL: Bug-Tracker, https://github.com/xia2/fp3/issues
Keywords: dials
Platform: UNKNOWN
Classifier: Development Status :: 3 - Alpha
Classifier: License :: OSI Approved :: BSD License
Classifier: Natural Language :: English
Classifier: Programming Language :: Python :: 3
Classifier: Programming Language :: Python :: 3.6
Classifier: Programming Language :: Python :: 3.7
Classifier: Programming Language :: Python :: 3.8
Classifier: Programming Language :: Python :: 3.9
Requires-Python: >=3.6
